MANIFEST.in
README.rst
setup.py
docs/HISTORY.txt
docs/LICENSE.GPL
docs/LICENSE.txt
ftw/__init__.py
ftw.xlsxsaveadapter.egg-info/PKG-INFO
ftw.xlsxsaveadapter.egg-info/SOURCES.txt
ftw.xlsxsaveadapter.egg-info/dependency_links.txt
ftw.xlsxsaveadapter.egg-info/entry_points.txt
ftw.xlsxsaveadapter.egg-info/namespace_packages.txt
ftw.xlsxsaveadapter.egg-info/not-zip-safe
ftw.xlsxsaveadapter.egg-info/requires.txt
ftw.xlsxsaveadapter.egg-info/top_level.txt
ftw/xlsxsaveadapter/__init__.py
ftw/xlsxsaveadapter/configure.zcml
ftw/xlsxsaveadapter/lawgiver.zcml
ftw/xlsxsaveadapter/testing.py
ftw/xlsxsaveadapter/xlsx_data_adapter.py
ftw/xlsxsaveadapter/Extensions/__init__.py
ftw/xlsxsaveadapter/Extensions/install.py
ftw/xlsxsaveadapter/locales/ftw.xlsxsaveadapter.pot
ftw/xlsxsaveadapter/locales/de/LC_MESSAGES/ftw.xlsxsaveadapter.po
ftw/xlsxsaveadapter/profiles/default/factorytool.xml
ftw/xlsxsaveadapter/profiles/default/metadata.xml
ftw/xlsxsaveadapter/profiles/default/rolemap.xml
ftw/xlsxsaveadapter/profiles/default/types.xml
ftw/xlsxsaveadapter/profiles/default/types/FormFolder.xml
ftw/xlsxsaveadapter/profiles/default/types/XlsxDataAdapter.xml
ftw/xlsxsaveadapter/profiles/uninstall/.gitkeep
ftw/xlsxsaveadapter/profiles/uninstall/factorytool.xml
ftw/xlsxsaveadapter/profiles/uninstall/rolemap.xml
ftw/xlsxsaveadapter/profiles/uninstall/types.xml
ftw/xlsxsaveadapter/profiles/uninstall/types/FormFolder.xml
ftw/xlsxsaveadapter/tests/__init__.py
ftw/xlsxsaveadapter/tests/builders.py
ftw/xlsxsaveadapter/tests/test_profiles.py
ftw/xlsxsaveadapter/tests/test_uninstall.py
ftw/xlsxsaveadapter/tests/test_xlsx_adapter.py
ftw/xlsxsaveadapter/upgrades/__init__.py