Metadata-Version: 1.1
Name: ftw.xlsxsaveadapter
Version: 1.0.1
Summary: Excel adapter for PloneFormGen
Home-page: https://github.com/4teamwork/ftw.xlsxsaveadapter
Author: 4teamwork AG
Author-email: mailto:info@4teamwork.ch
License: GPL2
Keywords: ftw xlsxsaveadapter
Platform: UNKNOWN
Classifier: Framework :: Plone
Classifier: Framework :: Plone :: 4.3
Classifier: License :: OSI Approved :: GNU General Public License (GPL)
Classifier: Programming Language :: Python
Classifier: Programming Language :: Python :: 2.7
Classifier: Topic :: Software Development :: Libraries :: Python Modules
